byterover/__init__.py
byterover/__main__.py
byterover/config.py
byterover/config.toml
byterover/exception.py
byterover/token_flow.py
byterover/_utils/__init__.py
byterover/_utils/async_utils.py
byterover/_utils/deprecation.py
byterover/_utils/http_utils.py
byterover/_utils/logger.py
byterover/api/__init__.py
byterover/api/client.py
byterover/api/listen_socket.py
byterover/api/core/__init__.py
byterover/api/core/api_error.py
byterover/api/core/client_wrapper.py
byterover/api/core/datetime_utils.py
byterover/api/core/file.py
byterover/api/core/http_client.py
byterover/api/core/jsonable_encoder.py
byterover/api/core/pydantic_utilities.py
byterover/api/core/query_encoder.py
byterover/api/core/remove_none_from_dict.py
byterover/api/core/request_options.py
byterover/api/resource/__init__.py
byterover/api/resource/commons/__init__.py
byterover/api/resource/commons/errors/__init__.py
byterover/api/resource/commons/errors/access_denied_error.py
byterover/api/resource/commons/errors/error.py
byterover/api/resource/commons/errors/method_not_allowed_error.py
byterover/api/resource/commons/errors/not_found_error.py
byterover/api/resource/commons/errors/unauthorized_error.py
byterover/api/resource/llm_keys/__init__.py
byterover/api/resource/llm_keys/client.py
byterover/api/resource/llm_keys/types/__init__.py
byterover/api/resource/llm_keys/types/llm_key.py
byterover/api/resource/notes/__init__.py
byterover/api/resource/notes/client.py
byterover/api/resource/notes/types/__init__.py
byterover/api/resource/notes/types/note_check.py
byterover/api/resource/organizations/__init__.py
byterover/api/resource/organizations/client.py
byterover/api/resource/organizations/types/__init__.py
byterover/api/resource/organizations/types/organization.py
byterover/api/resource/organizations/types/organizations.py
byterover/api/resource/projects/__init__.py
byterover/api/resource/projects/client.py
byterover/api/resource/projects/types/__init__.py
byterover/api/resource/projects/types/project.py
byterover-0.1.7.dist-info/LICENSE
byterover-0.1.7.dist-info/METADATA
byterover-0.1.7.dist-info/WHEEL
byterover-0.1.7.dist-info/entry_points.txt
byterover-0.1.7.dist-info/top_level.txt
byterover-0.1.7.dist-info/RECORD
